examples/ex_tb/light_manager.v
`timescale 100ms / 10ms

module light_manager(
    input clk,
    input enabled,
    output reg light);

always @(posedge clk) begin
    if(enabled) begin
        light <= ~light;
    end
    else begin
        light <= 0;
    end
end


endmodule

verilog/testbench/ex_tb/tb.v
`timescale 100ms / 10ms

module tb();

reg clk;
reg enabled;
wire light;

light_manager light_instance(clk, enabled, light);

//1 Hz = 1000ms period
localparam CLK_HALF_PERIOD = 5;

initial begin
    $dumpfile("$DUMP_FILENAME");
    $dumpvars(0, tb);
    clk = 0;
    enabled = 1;
    #100;
    enabled = 0;
    #100;
    enabled = 1;
    #100;
    $finish;
end

always begin
  #CLK_HALF_PERIOD
  clk = ~clk;
end

endmodule

waveforms/ex_tb_wave.vcd
$version Generated by VerilatedVcd $end
$timescale 10ms $end
 $scope module tb $end
  $var wire 1 # clk $end
  $var wire 1 $ enabled $end
  $var wire 1 % light $end
  $var wire 32 & CLK_HALF_PERIOD [31:0] $end
  $scope module light_instance $end
   $var wire 1 # clk $end
   $var wire 1 $ enabled $end
   $var wire 1 % light $end
  $upscope $end
 $upscope $end
$enddefinitions $end


#0
0#
1$
0%
b00000000000000000000000000000101 &
#50
1#
1%
#100
0#
#150
1#
0%
#200
0#
#250
1#
1%
#300
0#
#350
1#
0%
#400
0#
#450
1#
1%
#500
0#
#550
1#
0%
#600
0#
#650
1#
1%
#700
0#
#750
1#
0%
#800
0#
#850
1#
1%
#900
0#
#950
1#
0%
#1000
0#
0$
#1050
1#
#1100
0#
#1150
1#
#1200
0#
#1250
1#
#1300
0#
#1350
1#
#1400
0#
#1450
1#
#1500
0#
#1550
1#
#1600
0#
#1650
1#
#1700
0#
#1750
1#
#1800
0#
#1850
1#
#1900
0#
#1950
1#
#2000
0#
1$
#2050
1#
1%
#2100
0#
#2150
1#
0%
#2200
0#
#2250
1#
1%
#2300
0#
#2350
1#
0%
#2400
0#
#2450
1#
1%
#2500
0#
#2550
1#
0%
#2600
0#
#2650
1#
1%
#2700
0#
#2750
1#
0%
#2800
0#
#2850
1#
1%
#2900
0#
#2950
1#
0%
